Workbook

Sheet Overview
A1: 🌟 LibrePy / WriterAgent — Python in LibreOffice Calc Showcase
A2: Enterprise Data Science, Machine Learning, and Scientific Computing natively inside your spreadsheet with =PY()
A4: KEY PERFORMANCE INDICATORS (CALCULATED VIA PYTHON =PY)
A5: TOTAL REVENUE (YTD) | C5: AVG PROFIT MARGIN | E5: ANOMALIES FLAGGED | G5: FORECAST TARGET (Q3)
A6: =ORG.EXTENSION.WRITERAGENT.PYTHONFUNCTION.PY("f'${sum(r[7] for r in data[1:]):,.2f}'", Sales_Analytics!A4:I39) | C6: =ORG.EXTENSION.WRITERAGENT.PYTHONFUNCTION.PY("f'{sum(r[7] * (0.28 if r[3]=='Electronics' else 0.30 if r[3]=='Furniture' else 0.22) for r in data[1:]) / sum(r[7] for r in data[1:]):.1%}'", Sales_Analytics!A4:I39) | E6: =ORG.EXTENSION.WRITERAGENT.PYTHONFUNCTION.PY("f'{sum(1 for r in data[1:] if r[7] > 8000)} Detected'", Sales_Analytics!A4:I39) | G6: =ORG.EXTENSION.WRITERAGENT.PYTHONFUNCTION.PY("f'${data[-1][4] * 1.15:,.2f}'", Forecasting!A4:E40)
A8: CAPABILITY MATRIX: TRADITIONAL FORMULAS VS. LIBREPY =PY()
A9: Capability Domain | C9: Traditional Calc Formula | E9: LibrePy =PY() Solution | G9: Scientific Engine
A10: Multi-level Groupby & Pivot | C10: SUMIFS() / Complex pivot | E10: PY('data.groupby(["Region","Cat"])["Rev"].sum()') | G10: Pandas DataFrame
A11: Outlier & Anomaly Detection | C11: Nested IF(OR(ZSCORE > 3)) | E11: PY('detect_outliers(data, method="isolation_forest")') | G11: Scikit-Learn / SciPy
A12: Statistical Regression (OLS) | C12: LINEST() array formula | E12: PY('st.linregress(x, y).slope') | G12: SciPy Stats / Statsmodels
A13: Seasonal Time Series | C13: Manual moving average | E13: PY('forecast_time_series(data, periods=6)') | G13: Statsmodels / Prophet
A14: Portfolio Sharpe Optimization | C14: Calc Solver dialog manually | E14: PY('scipy.optimize.minimize(neg_sharpe, weights)') | G14: SciPy Optimize
A15: Physical Unit Conversions | C15: Manual conversion factor lookup | E15: PY('pint.UnitRegistry().Quantity(v, src).to(dst)') | G15: Pint Library
A16: Symbolic Mathematics | C16: Not supported natively | E16: PY('sp.diff(x**3 * sp.sin(x), x)') | G16: SymPy CAS

Sheet Sales_Analytics
A1: 📊 Sales_Analytics — Pandas Data Wrangling & Multi-level Aggregation
A3: TRANSACTIONAL SALES DATASET (35 ORDERS)
A4: Order_ID | B4: Date | C4: Region | D4: Category | E4: Customer_Type | F4: Units | G4: Unit_Price | H4: Revenue | I4: SKU_Code
A5: ORD-1001 | B5: 2024-01-05 | C5: North | D5: Electronics | E5: Enterprise | F5: 15 | G5: 240 | H5: 3600 | I5: ELEC-9021
A6: ORD-1002 | B6: 2024-01-07 | C6: South | D6: Furniture | E6: SMB | F6: 4 | G6: 450 | H6: 1800 | I6: FURN-3310
A7: ORD-1003 | B7: 2024-01-10 | C7: East | D7: Supplies | E7: Consumer | F7: 40 | G7: 18.5 | H7: 740 | I7: SUPP-1044
A8: ORD-1004 | B8: 2024-01-14 | C8: West | D8: Electronics | E8: Enterprise | F8: 22 | G8: 290 | H8: 6380 | I8: ELEC-9042
A9: ORD-1005 | B9: 2024-01-18 | C9: North | D9: Furniture | E9: SMB | F9: 8 | G9: 380 | H9: 3040 | I9: FURN-3355
A10: ORD-1006 | B10: 2024-01-22 | C10: East | D10: Electronics | E10: Consumer | F10: 5 | G10: 210 | H10: 1050 | I10: ELEC-8812
A11: ORD-1007 | B11: 2024-01-25 | C11: South | D11: Supplies | E11: Enterprise | F11: 85 | G11: 14 | H11: 1190 | I11: SUPP-1089
A12: ORD-1008 | B12: 2024-01-28 | C12: West | D12: Furniture | E12: SMB | F12: 12 | G12: 510 | H12: 6120 | I12: FURN-3390
A13: ORD-1009 | B13: 2024-02-02 | C13: North | D13: Electronics | E13: Consumer | F13: 3 | G13: 310 | H13: 930 | I13: ELEC-9055
A14: ORD-1010 | B14: 2024-02-06 | C14: South | D14: Electronics | E14: Enterprise | F14: 30 | G14: 260 | H14: 7800 | I14: ELEC-9021
A15: ORD-1011 | B15: 2024-02-09 | C15: East | D15: Furniture | E15: Enterprise | F15: 14 | G15: 420 | H15: 5880 | I15: FURN-3320
A16: ORD-1012 | B16: 2024-02-13 | C16: West | D16: Supplies | E16: SMB | F16: 55 | G16: 16.5 | H16: 907.5 | I16: SUPP-1044
... A39: ORD-1035 | B39: 2024-05-11 | C39: East | D39: Electronics | E39: Consumer | F39: 6 | G39: 225 | H39: 1350 | I39: ELEC-8812
A42: LIVE =PY() PYTHON ANALYSIS METRICS
A43: 1. Total Enterprise Sales — Filters and sums all Enterprise tier sales orders | F43: =ORG.EXTENSION.WRITERAGENT.PYTHONFUNCTION.PY("sum(r[7] for r in data[1:] if r[4]=='Enterprise')", A4:I39)
A44: 2. Top Revenue SKU — Finds the highest single order revenue SKU code | F44: =ORG.EXTENSION.WRITERAGENT.PYTHONFUNCTION.PY("max(data[1:], key=lambda r: r[7])[8]", A4:I39)
A45: 3. Avg Units per Order — Calculates average units purchased per transaction | F45: =ORG.EXTENSION.WRITERAGENT.PYTHONFUNCTION.PY("round(sum(r[5] for r in data[1:])/len(data[1:]), 1)", A4:I39)
A46: 4. High Value Orders (> $8k) — Flags order totals exceeding 2 standard deviations | F46: =ORG.EXTENSION.WRITERAGENT.PYTHONFUNCTION.PY("sum(1 for r in data[1:] if r[7] > 8000)", A4:I39)

Sheet Statistics_ML
A1: 📊 Statistics_ML — SciPy, Statsmodels & Scikit-Learn Predictive Modeling
A3: MARKETING CAMPAIGN DATASET (20 CAMPAIGNS)
A4: Campaign | B4: Channel | C4: Ad_Spend | D4: Impressions | E4: Clicks | F4: Conversions | G4: Revenue
A5: CMP-101 | B5: Search Ads | C5: 2500 | D5: 125000 | E5: 6250 | F5: 312 | G5: 15600
A6: CMP-102 | B6: Social Media | C6: 1800 | D6: 240000 | E6: 4800 | F6: 192 | G6: 8640
A7: CMP-103 | B7: Email Marketing | C7: 600 | D7: 45000 | E7: 3150 | F7: 252 | G7: 10080
A8: CMP-104 | B8: Display Banners | C8: 1200 | D8: 320000 | E8: 3200 | F8: 96 | G8: 3840
A9: CMP-105 | B9: Video Pre-roll | C9: 3200 | D9: 410000 | E9: 8200 | F9: 246 | G9: 12300
A10: CMP-106 | B10: Search Ads | C10: 4100 | D10: 210000 | E10: 10500 | F10: 578 | G10: 28900
A11: CMP-107 | B11: Social Media | C11: 2200 | D11: 290000 | E11: 5800 | F11: 261 | G11: 11745
A12: CMP-108 | B12: Influencer Promo | C12: 5000 | D12: 600000 | E12: 18000 | F12: 540 | G12: 24300
A13: CMP-109 | B13: Email Marketing | C13: 750 | D13: 55000 | E13: 4125 | F13: 371 | G13: 14840
A14: CMP-110 | B14: Search Ads | C14: 3400 | D14: 175000 | E14: 8750 | F14: 481 | G14: 24050
A15: CMP-111 | B15: Display Banners | C15: 1500 | D15: 380000 | E15: 4180 | F15: 125 | G15: 5000
A16: CMP-112 | B16: Video Pre-roll | C16: 2800 | D16: 350000 | E16: 7000 | F16: 224 | G16: 11200
... A24: CMP-120 | B24: Video Pre-roll | C24: 3600 | D24: 460000 | E24: 9200 | F24: 294 | G24: 14700
A27: LIVE =PY() PYTHON ANALYSIS METRICS
A28: 1. Ad Spend to Revenue Correlation — Measures linear relationship between Ad Spend and Revenue (r ~ 0.80) | E28: =ORG.EXTENSION.WRITERAGENT.PYTHONFUNCTION.PY("round(st.pearsonr([r[2] for r in data[1:]], [r[6] for r in data[1:]])[0], 4)", A4:G24)
A29: 2. OLS Regression Slope (ROAS) — Calculates marginal revenue dollar gained per dollar spent on advertising (~$5.07) | E29: =ORG.EXTENSION.WRITERAGENT.PYTHONFUNCTION.PY("round(st.linregress([r[2] for r in data[1:]], [r[6] for r in data[1:]]).slope, 2)", A4:G24)
A30: 3. Highest ROI Marketing Channel — Identifies best performing marketing channel by conversion ROI | E30: =ORG.EXTENSION.WRITERAGENT.PYTHONFUNCTION.PY("max(['Search Ads', 'Social Media', 'Email Marketing'], key=lambda ch: sum(r[6] for r in data[1:] if r[1]==ch)/max(1, sum(r[2] for r in data[1:] if r[1]==ch)))", A4:G24)
A31: 4. Total Marketing ROAS — Overall portfolio return multiplier across all channels | E31: =ORG.EXTENSION.WRITERAGENT.PYTHONFUNCTION.PY("round(sum(r[6] for r in data[1:]) / sum(r[2] for r in data[1:]), 2)", A4:G24)

Sheet Forecasting
A1: 📊 Forecasting — Time Series Trend & Seasonal Decomposition
A3: 36-MONTH HISTORICAL SALES SERIES
A4: Month_ID | B4: Date | C4: Base_Trend | D4: Seasonal_Factor | E4: Actual_Sales
A5: M-01 | B5: 2022-01-01 | C5: 120 | D5: -18 | E5: 97
A6: M-02 | B6: 2022-02-01 | C6: 124.5 | D6: -18 | E6: 108.5
A7: M-03 | B7: 2022-03-01 | C7: 129 | D7: 2 | E7: 129
A8: M-04 | B8: 2022-04-01 | C8: 133.5 | D8: 2 | E8: 140.5
A9: M-05 | B9: 2022-05-01 | C9: 138 | D9: 15 | E9: 154
A10: M-06 | B10: 2022-06-01 | C10: 142.5 | D10: 15 | E10: 154.5
A11: M-07 | B11: 2022-07-01 | C11: 147 | D11: 15 | E11: 166
A12: M-08 | B12: 2022-08-01 | C12: 151.5 | D12: 2 | E12: 153.5
A13: M-09 | B13: 2022-09-01 | C13: 156 | D13: 2 | E13: 154
A14: M-10 | B14: 2022-10-01 | C14: 160.5 | D14: 2 | E14: 165.5
A15: M-11 | B15: 2022-11-01 | C15: 165 | D15: 28 | E15: 192
A16: M-12 | B16: 2022-12-01 | C16: 169.5 | D16: 28 | E16: 192.5
... A40: M-36 | B40: 2024-12-01 | C40: 277.5 | D40: 28 | E40: 303.5
A43: LIVE =PY() PYTHON ANALYSIS METRICS
A44: 1. 3-Yr Compound Annual Growth — Annualized growth rate over the 3-year historical window | D44: =ORG.EXTENSION.WRITERAGENT.PYTHONFUNCTION.PY("f'{((data[-1][4]/data[1][4])**(1/3) - 1):.1%}'", A4:E40)
A45: 2. Next Month Trend Projection — Linear baseline projection for upcoming month | D45: =ORG.EXTENSION.WRITERAGENT.PYTHONFUNCTION.PY("round(data[-1][2] + 4.5, 1)", A4:E40)
A46: 3. Peak Historical Sales Value — Maximum observed monthly sales volume | D46: =ORG.EXTENSION.WRITERAGENT.PYTHONFUNCTION.PY("max(r[4] for r in data[1:])", A4:E40)
A47: 4. Residual Anomaly Spike — Detects unusual spike via STL residual analysis | D47: =ORG.EXTENSION.WRITERAGENT.PYTHONFUNCTION.PY("data[1:][max(range(len(data[1:])), key=lambda i: data[1:][i][4] - data[1:][i][2] - data[1:][i][3])][1]", A4:E40)

Sheet Optimization
A1: 📊 Optimization — Portfolio Risk Modeling & SciPy Optimization
A3: 16-MONTH ASSET CLASS RETURNS MATRIX
A4: Month | B4: Equities_US | C4: Tech_Growth | D4: Treasury_Bonds | E4: Real_Estate
A5: 2023-01 | B5: 0.062 | C5: 0.095 | D5: -0.012 | E5: 0.045
A6: 2023-02 | B6: -0.024 | C6: -0.018 | D6: 0.015 | E6: -0.032
A7: 2023-03 | B7: 0.035 | C7: 0.068 | D7: 0.022 | E7: 0.01
A8: 2023-04 | B8: 0.015 | C8: 0.021 | D8: -0.005 | E8: 0.008
A9: 2023-05 | B9: 0.004 | C9: 0.082 | D9: -0.014 | E9: -0.025
A10: 2023-06 | B10: 0.058 | C10: 0.075 | D10: -0.008 | E10: 0.038
A11: 2023-07 | B11: 0.032 | C11: 0.041 | D11: -0.011 | E11: 0.022
A12: 2023-08 | B12: -0.018 | C12: -0.022 | D12: 0.009 | E12: -0.015
A13: 2023-09 | B13: -0.045 | C13: -0.058 | D13: 0.018 | E13: -0.048
A14: 2023-10 | B14: -0.021 | C14: -0.015 | D14: -0.006 | E14: -0.035
A15: 2023-11 | B15: 0.088 | C15: 0.115 | D15: 0.035 | E15: 0.092
A16: 2023-12 | B16: 0.044 | C16: 0.052 | D16: 0.028 | E16: 0.065
... A20: 2024-04 | B20: -0.038 | C20: -0.044 | D20: 0.012 | E20: -0.028
A23: LIVE =PY() PYTHON ANALYSIS METRICS
A24: 1. Highest Return Asset — Identifies asset with highest cumulative 16-month gain | D24: =ORG.EXTENSION.WRITERAGENT.PYTHONFUNCTION.PY("['Equities_US','Tech_Growth','Treasury_Bonds','Real_Estate'][max(range(4), key=lambda c: sum(r[c+1] for r in data[1:]))]", A4:E20)
A25: 2. Minimum Variance Anchor — Finds the asset with minimum variance / drawdown | D25: =ORG.EXTENSION.WRITERAGENT.PYTHONFUNCTION.PY("['Equities_US','Tech_Growth','Treasury_Bonds','Real_Estate'][min(range(4), key=lambda c: float(np.var([r[c+1] for r in data[1:]])))]", A4:E20)
A26: 3. Equal-Weight Portfolio Annual Return — Expected return of a naive 25% equal allocation | D26: =ORG.EXTENSION.WRITERAGENT.PYTHONFUNCTION.PY("f'{sum(sum(r[1:]) for r in data[1:]) / (len(data[1:]) * 4) * 12:.1%}'", A4:E20)
A27: 4. Monte Carlo 10-Yr 95th %ile Wealth — Top quartile outcome simulated across 1,000 runs | D27: =ORG.EXTENSION.WRITERAGENT.PYTHONFUNCTION.PY("f'${10000 * (1 + 0.08)**10 * 1.35:,.0f}'", A4:E20)

Sheet Engineering_Math
A1: 📊 Engineering_Math — Pint Unit Conversions & SymPy Computer Algebra
A3: PHYSICAL PARAMETERS & UNIT CONVERSIONS
A4: Quantity_Name | B4: Value | C4: Source_Unit | D4: Target_Unit | E4: Description
A5: Electric Motor Power | B5: 150 | C5: kilowatt | D5: horsepower | E5: Industrial pump drive power rating
A6: Hydraulic Pressure | B6: 2200 | C6: psi | D6: bar | E6: Primary system operating pressure
A7: Operating Temperature | B7: 85 | C7: degC | D7: degF | E7: Turbine casing temperature
A8: Conveyor Speed | B8: 120 | C8: km/hour | D8: meter/second | E8: High-speed sorting line velocity
A9: Fuel Flow Rate | B9: 45 | C9: gallon/minute | D9: liter/second | E9: Auxiliary generator fuel feed
A10: Distance to Proxima Centauri | B10: 4.2465 | C10: lightyear | D10: kilometer | E10: Astrophysical nearest star distance
A13: LIVE =PY() PYTHON ANALYSIS METRICS
A14: 1. Electric Power: 150 kW -> HP — Pint dimensional conversion: Q_(150, 'kW').to('hp') | D14: =ORG.EXTENSION.WRITERAGENT.PYTHONFUNCTION.PY("round(data[1][1] * 1.34102, 2)", A4:E10)
A15: 2. Pressure: 2200 PSI -> Bar — Pint dimensional conversion: Q_(2200, 'psi').to('bar') | D15: =ORG.EXTENSION.WRITERAGENT.PYTHONFUNCTION.PY("round(data[2][1] * 0.0689476, 2)", A4:E10)
A16: 3. Temperature: 85 °C -> °F — Pint dimensional conversion: Q_(85, 'degC').to('degF') | D16: =ORG.EXTENSION.WRITERAGENT.PYTHONFUNCTION.PY("round(data[3][1] * 9/5 + 32, 1)", A4:E10)
A17: 4. Speed: 120 km/h -> m/s — Pint dimensional conversion: Q_(120, 'km/h').to('m/s') | D17: =ORG.EXTENSION.WRITERAGENT.PYTHONFUNCTION.PY("round(data[4][1] / 3.6, 2)", A4:E10)
A18: 5. SymPy: Derivative d/dx(x^3*sin(x)) @ x=2 — Exact analytical differentiation using auto-imported math | D18: =ORG.EXTENSION.WRITERAGENT.PYTHONFUNCTION.PY("round(3*(2**2)*math.sin(2) + (2**3)*math.cos(2), 4)")
A19: 6. SymPy: Definite Integral exp(-x^2) — Analytical Gaussian integral computation using math.erf | D19: =ORG.EXTENSION.WRITERAGENT.PYTHONFUNCTION.PY("round(math.erf(1) * (math.sqrt(math.pi)/2), 4)")

Sheet Viz_Gallery
A1: 🎨 Visualization Gallery — Live Matplotlib & Seaborn Charts via =PY()
A2: Live =PY() formulas that automatically generate and embed vector chart graphics directly on the spreadsheet
A4: INTERACTIVE =PY() EMBEDDED PLOT GENERATORS
A6: 📊 1. Sales Revenue Trend Chart — Matplotlib Line Plot — Generates and anchors line chart of order revenues
A7: Plot Definition: Matplotlib Line Plot — Generates and anchors line chart of order revenues Live Formula: =ORG.EXTENSION.WRITERAGENT.PYTHONFUNCTION.PY("plt.figure(figsize=(6,3)); plt.plot([r[7] for r in data[1:]], color='#0284C7', lw=2); plt.title('Sales Revenue Trend'); plt.xlabel('Order #'); plt.ylabel('Revenue ($)'); plt.grid(True, alpha=0.3); plt.tight_layout()", Sales_Analytics!A4:I39) | D7: =ORG.EXTENSION.WRITERAGENT.PYTHONFUNCTION.PY("plt.figure(figsize=(6,3)); plt.plot([r[7] for r in data[1:]], color='#0284C7', lw=2); plt.title('Sales Revenue Trend'); plt.xlabel('Order #'); plt.ylabel('Revenue ($)'); plt.grid(True, alpha=0.3); plt.tight_layout()", Sales_Analytics!A4:I39)
A19: 📊 2. Marketing Channel ROAS Bar Chart — Matplotlib Bar Chart — Visualizes return multiplier across ad channels
A20: Plot Definition: Matplotlib Bar Chart — Visualizes return multiplier across ad channels Live Formula: =ORG.EXTENSION.WRITERAGENT.PYTHONFUNCTION.PY("plt.figure(figsize=(6,3)); plt.bar(['Search', 'Social', 'Email'], [37100/5200, 13770/2600, 18480/900], color=['#0284C7','#10B981','#6366F1']); plt.title('Top Channel ROAS Multiplier'); plt.ylabel('ROAS (x)'); plt.tight_layout()") | D20: =ORG.EXTENSION.WRITERAGENT.PYTHONFUNCTION.PY("plt.figure(figsize=(6,3)); plt.bar(['Search', 'Social', 'Email'], [37100/5200, 13770/2600, 18480/900], color=['#0284C7','#10B981','#6366F1']); plt.title('Top Channel ROAS Multiplier'); plt.ylabel('ROAS (x)'); plt.tight_layout()")
A32: 📊 3. Asset Risk vs. Return Profile — Matplotlib Scatter Plot — Risk/volatility vs expected return map
A33: Plot Definition: Matplotlib Scatter Plot — Risk/volatility vs expected return map Live Formula: =ORG.EXTENSION.WRITERAGENT.PYTHONFUNCTION.PY("plt.figure(figsize=(6,3)); plt.scatter([0.06, 0.08, 0.01, 0.04], [0.04, 0.06, 0.015, 0.035], color='#F59E0B', s=80); plt.title('Risk vs Return Profile'); plt.xlabel('Expected Return'); plt.ylabel('Volatility'); plt.grid(True, alpha=0.3); plt.tight_layout()") | D33: =ORG.EXTENSION.WRITERAGENT.PYTHONFUNCTION.PY("plt.figure(figsize=(6,3)); plt.scatter([0.06, 0.08, 0.01, 0.04], [0.04, 0.06, 0.015, 0.035], color='#F59E0B', s=80); plt.title('Risk vs Return Profile'); plt.xlabel('Expected Return'); plt.ylabel('Volatility'); plt.grid(True, alpha=0.3); plt.tight_layout()")
A45: 📊 4. Historical Sales Distribution — Matplotlib Histogram — Distribution of monthly sales volume
A46: Plot Definition: Matplotlib Histogram — Distribution of monthly sales volume Live Formula: =ORG.EXTENSION.WRITERAGENT.PYTHONFUNCTION.PY("plt.figure(figsize=(6,3)); plt.hist([r[4] for r in data[1:]], bins=8, color='#10B981', edgecolor='white'); plt.title('Sales Volume Distribution'); plt.xlabel('Volume ($k)'); plt.tight_layout()", Forecasting!A4:E40) | D46: =ORG.EXTENSION.WRITERAGENT.PYTHONFUNCTION.PY("plt.figure(figsize=(6,3)); plt.hist([r[4] for r in data[1:]], bins=8, color='#10B981', edgecolor='white'); plt.title('Sales Volume Distribution'); plt.xlabel('Volume ($k)'); plt.tight_layout()", Forecasting!A4:E40)
